cnslab/__init__.py
cnslab/codes.py
cnslabnew-0.1.1.dist-info/METADATA
cnslabnew-0.1.1.dist-info/WHEEL
cnslabnew-0.1.1.dist-info/top_level.txt
cnslabnew-0.1.1.dist-info/RECORD
