Metadata-Version: 2.1
Name: cnslabnew
Version: 0.1.1
Summary: A Python library with various useful CNS code snippets.
Home-page: https://github.com/mdimado/aimllab
Author: mdimado
Author-email: mdimad005@gmail.com
Classifier: Programming Language :: Python :: 3
Classifier: Operating System :: OS Independent
Requires-Python: >=3.6
